{
  "book_id": "gtm055",
  "book_title": "Introduction to Operator Theory I: Elements of Functional Analysis",
  "author": "Arlen Brown, Carl Pearcy",
  "extraction_date": "2026-06-27",
  "total_concepts": 234,
  "total_exercises": 121,
  "sections": {
    "s001_Section_1.md": {
      "chapter": "1",
      "concepts": 0,
      "exercises": 10
    },
    "s002_Section_2.md": {
      "chapter": "2",
      "concepts": 0,
      "exercises": 0
    },
    "s003_Section_3.md": {
      "chapter": "2",
      "concepts": 2,
      "exercises": 0
    },
    "s004_Section_4.md": {
      "chapter": "3",
      "concepts": 10,
      "exercises": 0
    },
    "s005_Section_5.md": {
      "chapter": "3-4",
      "concepts": 8,
      "exercises": 0
    },
    "s006_Section_6.md": {
      "chapter": "4-5",
      "concepts": 13,
      "exercises": 16
    },
    "s007_Section_7.md": {
      "chapter": "5",
      "concepts": 0,
      "exercises": 0
    },
    "s008_Section_8.md": {
      "chapter": "6-7",
      "concepts": 15,
      "exercises": 10
    },
    "s009_Section_9.md": {
      "chapter": "7-8",
      "concepts": 19,
      "exercises": 0
    },
    "s010_Section_10.md": {
      "chapter": "8-9",
      "concepts": 12,
      "exercises": 12
    },
    "s011_Section_11.md": {
      "chapter": "10",
      "concepts": 13,
      "exercises": 0
    },
    "s012_Section_12.md": {
      "chapter": "10-11",
      "concepts": 34,
      "exercises": 2
    },
    "s013_Section_13.md": {
      "chapter": "11-12",
      "concepts": 15,
      "exercises": 0
    },
    "s014_Section_14.md": {
      "chapter": "12-13",
      "concepts": 3,
      "exercises": 12
    },
    "s015_Section_15.md": {
      "chapter": "13-14",
      "concepts": 10,
      "exercises": 0
    },
    "s016_Section_16.md": {
      "chapter": "15",
      "concepts": 13,
      "exercises": 13
    },
    "s017_Section_17.md": {
      "chapter": "16",
      "concepts": 15,
      "exercises": 9
    },
    "s018_Section_18.md": {
      "chapter": "16-17",
      "concepts": 21,
      "exercises": 14
    },
    "s019_Section_19.md": {
      "chapter": "18",
      "concepts": 12,
      "exercises": 0
    },
    "s020_Section_20.md": {
      "chapter": "18-19",
      "concepts": 19,
      "exercises": 23
    }
  }
}